pyspark_prometheus/__init__.py
pyspark_prometheus/listener.py
pyspark_prometheus-0.1.3.dist-info/LICENSE
pyspark_prometheus-0.1.3.dist-info/METADATA
pyspark_prometheus-0.1.3.dist-info/WHEEL
pyspark_prometheus-0.1.3.dist-info/RECORD
