Metadata-Version: 2.1
Name: pyspark-prometheus
Version: 0.1.3
Summary: Prometheus instrumentation for Spark Streaming metrics.
Home-page: https://github.com/zcking/pyspark_prometheus
License: MIT
Keywords: prometheus,spark,streaming,metrics
Author: Zachary King
Author-email: zach@makewithdata.tech
Requires-Python: >=3.9,<4.0
Classifier: License :: OSI Approved :: MIT License
Classifier: Programming Language :: Python :: 3
Classifier: Programming Language :: Python :: 3.9
Classifier: Programming Language :: Python :: 3.10
Classifier: Programming Language :: Python :: 3.11
Classifier: Programming Language :: Python :: 3.12
Requires-Dist: prometheus-client (>=0.21.0)
Requires-Dist: pyspark (>=3.5.0)
Project-URL: Repository, https://github.com/zcking/pyspark_prometheus
